{
    "solver_status": "Optimal",
    "custo_total": "$330301.95",
    "sumario_perdas": {
        "carga_total_pu": "37.7469",
        "perdas_totais_pu": "0.8372",
        "cargas_individuais_pu": {
            "1": "0.5239",
            "2": "0.1982",
            "3": "0.4001",
            "4": "0.2979",
            "5": "0.5734",
            "6": "0.2034",
            "7": "0.7551",
            "8": "0.4862",
            "9": "0.3284",
            "10": "0.1526",
            "11": "0.9007",
            "12": "0.2407",
            "13": "0.1094",
            "14": "0.6354",
            "15": "0.4770",
            "16": "0.1943",
            "17": "0.1516",
            "18": "0.1001",
            "19": "0.0769",
            "20": "0.6363",
            "21": "0.1796",
            "22": "0.2279",
            "23": "0.4718",
            "24": "0.5792",
            "25": "0.2220",
            "26": "0.5961",
            "27": "0.3167",
            "28": "0.3026",
            "29": "0.2811",
            "30": "0.1995",
            "31": "0.4073",
            "32": "0.3745",
            "33": "0.1882",
            "34": "0.1599",
            "35": "0.5525",
            "36": "0.2945",
            "37": "0.3517",
            "38": "0.2156",
            "39": "0.8808",
            "40": "0.1634",
            "41": "0.1780",
            "42": "0.1974",
            "43": "0.2171",
            "44": "1.1341",
            "45": "0.6809",
            "46": "0.8965",
            "47": "0.1339",
            "48": "0.1259",
            "49": "2.8580",
            "50": "0.7651",
            "51": "0.8499",
            "52": "0.3884",
            "53": "0.3013",
            "54": "0.6712",
            "55": "0.6927",
            "56": "0.5035",
            "57": "0.6891",
            "58": "0.6606",
            "59": "0.7206",
            "60": "0.4084",
            "61": "1.3114",
            "62": "0.5494",
            "63": "0.2071",
            "64": "0.1088",
            "65": "0.2315",
            "66": "0.2171",
            "67": "0.5076",
            "68": "0.8334",
            "69": "0.6147",
            "70": "0.1197",
            "71": "0.2930",
            "72": "0.4405",
            "73": "0.4127",
            "74": "0.1472",
            "75": "0.3610",
            "76": "0.3636",
            "77": "0.2209",
            "78": "0.0484",
            "79": "0.2266",
            "80": "0.4032",
            "81": "0.3406",
            "82": "0.4214",
            "83": "0.2932",
            "84": "0.0208",
            "85": "0.0886",
            "86": "0.3999",
            "87": "0.2436",
            "88": "0.0836",
            "89": "0.2158",
            "90": "0.2157",
            "91": "0.3267"
        },
        "perdas_por_barra_pu": {
            "1": "0.003012",
            "2": "0.001896",
            "3": "0.001899",
            "4": "0.001946",
            "5": "0.002585",
            "6": "0.001556",
            "7": "0.003073",
            "8": "0.002139",
            "9": "0.000000",
            "10": "0.000000",
            "11": "0.004196",
            "12": "0.003466",
            "13": "0.001259",
            "14": "0.000654",
            "15": "0.014564",
            "16": "0.000476",
            "17": "0.018380",
            "18": "0.001137",
            "19": "0.007472",
            "20": "0.001374",
            "21": "0.000144",
            "22": "0.000272",
            "23": "0.014269",
            "24": "0.006281",
            "25": "0.004746",
            "26": "0.000740",
            "27": "0.005238",
            "28": "0.000162",
            "29": "0.000530",
            "30": "0.002881",
            "31": "0.011582",
            "32": "0.014249",
            "33": "0.001427",
            "34": "0.000500",
            "35": "0.002124",
            "36": "0.000098",
            "37": "0.004364",
            "38": "0.001893",
            "39": "0.001935",
            "40": "0.013157",
            "41": "0.010129",
            "42": "0.020514",
            "43": "0.002711",
            "44": "0.004731",
            "45": "0.014299",
            "46": "0.007871",
            "47": "0.002672",
            "48": "0.000310",
            "49": "0.028171",
            "50": "0.000250",
            "51": "0.001003",
            "52": "0.000245",
            "53": "0.001211",
            "54": "0.017665",
            "55": "0.014250",
            "56": "0.038488",
            "57": "0.000377",
            "58": "0.001066",
            "59": "0.059139",
            "60": "0.000739",
            "61": "0.000784",
            "62": "0.004339",
            "63": "0.000040",
            "64": "0.001374",
            "65": "0.003911",
            "66": "0.023950",
            "67": "0.003929",
            "68": "0.000689",
            "69": "0.041509",
            "70": "0.012480",
            "71": "0.000003",
            "72": "0.000006",
            "73": "0.000000",
            "74": "0.002047",
            "75": "0.022568",
            "76": "0.005718",
            "77": "0.028020",
            "78": "0.000541",
            "79": "0.003593",
            "80": "0.044853",
            "81": "0.000004",
            "82": "0.006830",
            "83": "0.013154",
            "84": "0.007103",
            "85": "0.022043",
            "86": "0.000769",
            "87": "0.000000",
            "88": "0.007655",
            "89": "0.013163",
            "90": "0.002479",
            "91": "0.003636",
            "92": "0.012929",
            "93": "0.000767",
            "94": "0.009844",
            "95": "0.004012",
            "96": "0.018027",
            "97": "0.006243",
            "98": "0.015982",
            "99": "0.014946",
            "100": "0.036769",
            "101": "0.001479",
            "102": "0.002182",
            "103": "0.016425",
            "104": "0.007553",
            "105": "0.004965",
            "106": "0.007778",
            "107": "0.001062",
            "108": "0.000486",
            "109": "0.000175",
            "110": "0.004609",
            "111": "0.000000",
            "112": "0.000641",
            "113": "0.006419",
            "114": "0.000517",
            "115": "0.000045",
            "116": "0.000000",
            "117": "0.000730",
            "118": "0.001924"
        }
    },
    "sumario_curtailment": {
        "curtailment_total_pu": "0.0000",
        "curtailment_por_gerador": {
            "55": {
                "disponivel_pu": "0.0482",
                "despachado_pu": "0.0482",
                "curtailment_pu": "-0.0000"
            },
            "56": {
                "disponivel_pu": "0.0953",
                "despachado_pu": "0.0953",
                "curtailment_pu": "0.0000"
            },
            "57": {
                "disponivel_pu": "0.0245",
                "despachado_pu": "0.0245",
                "curtailment_pu": "-0.0000"
            },
            "58": {
                "disponivel_pu": "0.0832",
                "despachado_pu": "0.0832",
                "curtailment_pu": "-0.0000"
            },
            "59": {
                "disponivel_pu": "0.0623",
                "despachado_pu": "0.0623",
                "curtailment_pu": "0.0000"
            },
            "60": {
                "disponivel_pu": "0.0506",
                "despachado_pu": "0.0506",
                "curtailment_pu": "0.0000"
            },
            "61": {
                "disponivel_pu": "0.0060",
                "despachado_pu": "0.0060",
                "curtailment_pu": "-0.0000"
            },
            "62": {
                "disponivel_pu": "0.0119",
                "despachado_pu": "0.0119",
                "curtailment_pu": "0.0000"
            },
            "63": {
                "disponivel_pu": "0.1375",
                "despachado_pu": "0.1375",
                "curtailment_pu": "0.0000"
            },
            "64": {
                "disponivel_pu": "0.0322",
                "despachado_pu": "0.0322",
                "curtailment_pu": "0.0000"
            },
            "65": {
                "disponivel_pu": "0.1216",
                "despachado_pu": "0.1216",
                "curtailment_pu": "0.0000"
            }
        }
    },
    "primal_results": {
        "geracao_pu": {
            "1": "1.3000",
            "2": "0.2014",
            "3": "1.5000",
            "4": "1.9068",
            "5": "0.0000",
            "6": "0.0000",
            "7": "3.4979",
            "8": "0.0000",
            "9": "0.2020",
            "10": "0.9460",
            "11": "0.0000",
            "12": "0.0000",
            "13": "0.0000",
            "14": "0.0000",
            "15": "0.0000",
            "16": "0.0000",
            "17": "0.0000",
            "18": "0.0000",
            "19": "1.4000",
            "20": "1.2000",
            "21": "4.5000",
            "22": "3.6145",
            "23": "0.0463",
            "24": "0.0000",
            "25": "0.0000",
            "26": "0.0384",
            "27": "0.0000",
            "28": "0.0000",
            "29": "0.0000",
            "30": "3.2885",
            "31": "0.0000",
            "32": "0.0000",
            "33": "0.0000",
            "34": "0.0000",
            "35": "0.0000",
            "36": "0.0000",
            "37": "6.3446",
            "38": "3.0000",
            "39": "0.0000",
            "40": "0.0000",
            "41": "1.5542",
            "42": "0.0000",
            "43": "0.0000",
            "44": "0.0000",
            "45": "0.0000",
            "46": "0.3668",
            "47": "0.0000",
            "48": "0.0000",
            "49": "0.0000",
            "50": "0.0000",
            "51": "0.0000",
            "52": "0.0000",
            "53": "0.0000",
            "54": "0.0000",
            "55": "0.0482",
            "56": "0.0953",
            "57": "0.0245",
            "58": "0.0832",
            "59": "0.0623",
            "60": "0.0506",
            "61": "0.0060",
            "62": "0.0119",
            "63": "0.1375",
            "64": "0.0322",
            "65": "0.1216",
            "1001": "0.0000",
            "1002": "0.0000",
            "1003": "0.0000",
            "1004": "0.0000",
            "1005": "0.0000",
            "1006": "0.0000",
            "1007": "0.0000",
            "1008": "0.0000",
            "1009": "0.0000",
            "1010": "0.0000",
            "1011": "0.0000",
            "1012": "0.0000",
            "1013": "0.0000",
            "1014": "0.0000",
            "1015": "0.0000",
            "1016": "0.0000",
            "1017": "0.0000",
            "1018": "0.0000",
            "1019": "0.0602",
            "1020": "0.0000",
            "1021": "0.0000",
            "1022": "0.0000",
            "1023": "0.0000",
            "1024": "0.0000",
            "1025": "0.0000",
            "1026": "0.0000",
            "1027": "0.0000",
            "1028": "0.0000",
            "1029": "0.0000",
            "1030": "0.0000",
            "1031": "0.0000",
            "1032": "0.0000",
            "1033": "0.0000",
            "1034": "0.0000",
            "1035": "0.0000",
            "1036": "0.0000",
            "1037": "0.0000",
            "1038": "0.0000",
            "1039": "0.0000",
            "1040": "0.0000",
            "1041": "0.0000",
            "1042": "0.0000",
            "1043": "0.0000",
            "1044": "0.0000",
            "1045": "0.0000",
            "1046": "2.6915",
            "1047": "0.0000",
            "1048": "0.0000",
            "1049": "0.0000",
            "1050": "0.0000",
            "1051": "0.0000",
            "1052": "0.0000",
            "1053": "0.0000",
            "1054": "0.0000",
            "1055": "0.0000",
            "1056": "0.2515",
            "1057": "0.0000",
            "1058": "0.0000",
            "1059": "0.0000",
            "1060": "0.0000",
            "1061": "0.0000",
            "1062": "0.0000",
            "1063": "0.0000",
            "1064": "0.0000",
            "1065": "0.0000",
            "1066": "0.0000",
            "1067": "0.0000",
            "1068": "0.0000",
            "1069": "0.0000",
            "1070": "0.0000",
            "1071": "0.0000",
            "1072": "0.0000",
            "1073": "0.0000",
            "1074": "0.0000",
            "1075": "0.0000",
            "1076": "0.0000",
            "1077": "0.0000",
            "1078": "0.0000",
            "1079": "0.0000",
            "1080": "0.0000",
            "1081": "0.0000",
            "1082": "0.0000",
            "1083": "0.0000",
            "1084": "0.0000",
            "1085": "0.0000",
            "1086": "0.0000",
            "1087": "0.0000",
            "1088": "0.0000",
            "1089": "0.0000",
            "1090": "0.0000",
            "1091": "0.0000"
        },
        "thetas_deg": {
            "1": "-4.6532",
            "2": "-6.6585",
            "3": "-5.7973",
            "4": "-5.5240",
            "5": "-5.2853",
            "6": "-4.9881",
            "7": "-5.9761",
            "8": "-3.7555",
            "9": "-3.7555",
            "10": "-3.7555",
            "11": "-7.1942",
            "12": "-7.1888",
            "13": "-7.8552",
            "14": "-7.1814",
            "15": "-5.4490",
            "16": "-8.2183",
            "17": "-7.9528",
            "18": "-8.7379",
            "19": "-7.7065",
            "20": "-9.8553",
            "21": "-10.4626",
            "22": "-10.3132",
            "23": "-9.1540",
            "24": "-6.3351",
            "25": "-9.7181",
            "26": "-8.7735",
            "27": "-14.8539",
            "28": "-15.3483",
            "29": "-14.9224",
            "30": "-6.6432",
            "31": "-14.3397",
            "32": "-13.9024",
            "33": "-7.4468",
            "34": "-8.1576",
            "35": "-9.6796",
            "36": "-9.8566",
            "37": "-7.9097",
            "38": "-6.5679",
            "39": "-6.9859",
            "40": "-5.4774",
            "41": "-4.6522",
            "42": "0.8644",
            "43": "-7.1516",
            "44": "-2.9987",
            "45": "-0.6239",
            "46": "4.1565",
            "47": "2.6428",
            "48": "3.3518",
            "49": "3.7616",
            "50": "3.1472",
            "51": "2.3325",
            "52": "1.9268",
            "53": "2.6503",
            "54": "4.7160",
            "55": "3.3036",
            "56": "4.1688",
            "57": "3.3089",
            "58": "2.8163",
            "59": "-5.3486",
            "60": "-6.3230",
            "61": "-5.8231",
            "62": "-6.3158",
            "63": "-4.8700",
            "64": "-4.6220",
            "65": "-2.8917",
            "66": "-1.5039",
            "67": "-4.6897",
            "68": "-1.9750",
            "69": "0.0000",
            "70": "-6.6050",
            "71": "-6.5817",
            "72": "-6.4637",
            "73": "-6.5817",
            "74": "-8.1152",
            "75": "-6.9901",
            "76": "-8.9284",
            "77": "-4.5274",
            "78": "-4.8513",
            "79": "-4.4804",
            "80": "-1.7485",
            "81": "-1.8950",
            "82": "-6.3148",
            "83": "-4.7593",
            "84": "-1.7962",
            "85": "0.0682",
            "86": "-1.4674",
            "87": "-1.4674",
            "88": "-4.8844",
            "89": "-6.2396",
            "90": "-4.8809",
            "91": "-6.5777",
            "92": "-9.1331",
            "93": "-10.2634",
            "94": "-10.7339",
            "95": "-10.1345",
            "96": "-7.9859",
            "97": "-5.3507",
            "98": "-7.5589",
            "99": "-10.0976",
            "100": "-13.3231",
            "101": "-12.5126",
            "102": "-10.3662",
            "103": "-16.3311",
            "104": "-18.9984",
            "105": "-19.7969",
            "106": "-19.9840",
            "107": "-21.4330",
            "108": "-20.5203",
            "109": "-20.7815",
            "110": "-21.0849",
            "111": "-21.0849",
            "112": "-21.9805",
            "113": "-8.7307",
            "114": "-14.8580",
            "115": "-14.9703",
            "116": "-1.9750",
            "117": "-8.9249",
            "118": "-8.3803"
        },
        "fluxo_pu": {
            "1": "0.3503",
            "2": "0.4710",
            "3": "-0.5222",
            "4": "-0.0828",
            "5": "-0.0960",
            "6": "0.8290",
            "7": "0.0000",
            "8": "1.0000",
            "9": "0.0000",
            "10": "0.4237",
            "11": "0.4885",
            "12": "-0.0048",
            "13": "0.1503",
            "14": "0.1518",
            "15": "0.6225",
            "16": "0.1578",
            "17": "-0.0018",
            "18": "-0.1718",
            "19": "-0.1551",
            "20": "0.2154",
            "21": "1.0000",
            "22": "-0.0257",
            "23": "0.2713",
            "24": "-0.3652",
            "25": "0.3205",
            "26": "1.0000",
            "27": "0.1249",
            "28": "-0.0269",
            "29": "-0.1272",
            "30": "-1.0000",
            "31": "0.1231",
            "32": "0.4316",
            "33": "0.5499",
            "34": "0.1009",
            "35": "-0.0788",
            "36": "0.5891",
            "37": "1.0000",
            "38": "-0.4323",
            "39": "0.7132",
            "40": "-0.3073",
            "41": "0.7188",
            "42": "-0.0775",
            "43": "-0.2200",
            "44": "0.2803",
            "45": "0.0319",
            "46": "0.3027",
            "47": "-0.6216",
            "48": "0.0569",
            "50": "-0.4603",
            "51": "0.6245",
            "52": "-0.1521",
            "53": "-0.2527",
            "54": "-0.0243",
            "55": "-0.4352",
            "56": "-0.2957",
            "57": "-0.6048",
            "58": "-0.7132",
            "59": "-0.2954",
            "60": "-0.1044",
            "61": "-0.4600",
            "62": "-0.6153",
            "63": "0.2080",
            "64": "0.0743",
            "65": "-0.3124",
            "66": "-0.1565",
            "67": "-0.1565",
            "68": "-0.4115",
            "69": "-0.1416",
            "70": "0.1426",
            "71": "0.1821",
            "72": "0.1204",
            "73": "-0.0772",
            "74": "-0.2955",
            "75": "-0.0576",
            "76": "-0.0572",
            "77": "0.3487",
            "78": "1.0000",
            "79": "-1.0000",
            "80": "0.1554",
            "81": "-0.0211",
            "82": "0.2444",
            "83": "-0.1174",
            "84": "0.7661",
            "85": "0.6618",
            "86": "0.6950",
            "87": "0.6998",
            "88": "0.1173",
            "89": "0.0552",
            "90": "-0.6463",
            "91": "-0.0023",
            "92": "0.2287",
            "93": "0.2164",
            "94": "-0.2164",
            "95": "0.7822",
            "96": "-0.6507",
            "97": "-1.0000",
            "98": "1.0000",
            "99": "1.0000",
            "100": "-0.3852",
            "101": "-0.2426",
            "102": "-0.6546",
            "103": "0.5478",
            "104": "-1.0000",
            "105": "0.1660",
            "106": "0.2026",
            "107": "-0.9316",
            "108": "0.9077",
            "109": "0.0114",
            "110": "-0.0114",
            "111": "0.0115",
            "112": "-0.0114",
            "113": "0.0000",
            "114": "0.1992",
            "115": "0.0477",
            "116": "1.0000",
            "117": "-0.4837",
            "118": "-0.5190",
            "119": "0.7824",
            "120": "-0.2150",
            "121": "0.4559",
            "122": "-0.2653",
            "123": "-1.0000",
            "124": "-0.4619",
            "125": "-0.6773",
            "126": "-0.0691",
            "127": "-0.0691",
            "128": "0.3657",
            "129": "-0.7408",
            "130": "-0.3918",
            "131": "-0.5693",
            "132": "-0.5077",
            "133": "0.2179",
            "134": "0.0000",
            "135": "0.8474",
            "136": "0.6364",
            "137": "0.3322",
            "138": "-0.1261",
            "139": "-0.2379",
            "140": "0.3543",
            "141": "1.0000",
            "142": "0.3194",
            "143": "0.3506",
            "144": "0.2326",
            "145": "0.1768",
            "146": "0.1122",
            "147": "-0.2411",
            "148": "0.5981",
            "149": "0.5503",
            "150": "-0.5519",
            "151": "0.6731",
            "152": "0.9390",
            "153": "0.7074",
            "154": "0.2479",
            "155": "0.7791",
            "156": "-0.6855",
            "157": "-0.5197",
            "158": "0.5620",
            "159": "0.6924",
            "160": "-0.1121",
            "161": "0.3850",
            "162": "-0.3345",
            "163": "1.0000",
            "164": "0.4856",
            "165": "0.2939",
            "166": "0.3722",
            "167": "0.5077",
            "168": "0.3687",
            "169": "0.0597",
            "170": "0.1560",
            "171": "0.1796",
            "172": "0.1382",
            "173": "0.1583",
            "174": "0.4576",
            "175": "0.0695",
            "176": "0.0000",
            "177": "0.2442",
            "178": "0.4511",
            "179": "-0.4446",
            "180": "0.2725",
            "181": "0.0274",
            "182": "0.1884",
            "183": "0.0000",
            "184": "0.2164",
            "185": "0.5044",
            "186": "-0.1758"
        }
    },
    "dual_results": {
        "custo_marginal_de_energia_LMP": {
            "1": "$36673.60/pu",
            "2": "$35329.86/pu",
            "3": "$37243.91/pu",
            "4": "$40000.00/pu",
            "5": "$40547.85/pu",
            "6": "$37546.80/pu",
            "7": "$36390.85/pu",
            "8": "$800.00/pu",
            "9": "$800.00/pu",
            "10": "$800.00/pu",
            "11": "$35276.67/pu",
            "12": "$34501.30/pu",
            "13": "$27500.06/pu",
            "14": "$25720.00/pu",
            "15": "$1500.00/pu",
            "16": "$34374.38/pu",
            "17": "$34100.31/pu",
            "18": "$37085.62/pu",
            "19": "$40000.00/pu",
            "20": "$40000.00/pu",
            "21": "$40000.00/pu",
            "22": "$40000.00/pu",
            "23": "$40000.00/pu",
            "24": "$2400.00/pu",
            "25": "$34506.72/pu",
            "26": "$31530.52/pu",
            "27": "$36013.64/pu",
            "28": "$35884.86/pu",
            "29": "$35742.83/pu",
            "30": "$24830.17/pu",
            "31": "$35692.97/pu",
            "32": "$36548.30/pu",
            "33": "$9846.01/pu",
            "34": "$20000.17/pu",
            "35": "$19372.80/pu",
            "36": "$19372.80/pu",
            "37": "$19372.80/pu",
            "38": "$20255.19/pu",
            "39": "$18138.65/pu",
            "40": "$17434.25/pu",
            "41": "$16870.85/pu",
            "42": "$15309.05/pu",
            "43": "$17608.22/pu",
            "44": "$14116.33/pu",
            "45": "$12834.27/pu",
            "46": "$11829.99/pu",
            "47": "$11029.82/pu",
            "48": "$11621.01/pu",
            "49": "$11565.17/pu",
            "50": "$18557.65/pu",
            "51": "$20912.19/pu",
            "52": "$18263.00/pu",
            "53": "$10896.62/pu",
            "54": "$5400.00/pu",
            "55": "$40000.00/pu",
            "56": "$40000.00/pu",
            "57": "$31017.64/pu",
            "58": "$29057.08/pu",
            "59": "$38123.81/pu",
            "60": "$39318.42/pu",
            "61": "$40000.00/pu",
            "62": "$36948.27/pu",
            "63": "$41904.52/pu",
            "64": "$43863.44/pu",
            "65": "$14221.72/pu",
            "66": "$23481.00/pu",
            "67": "$29736.96/pu",
            "68": "$8889.88/pu",
            "69": "$6900.00/pu",
            "70": "$22687.51/pu",
            "71": "$20937.31/pu",
            "72": "$12063.06/pu",
            "73": "$20937.31/pu",
            "74": "$35934.72/pu",
            "75": "$40000.00/pu",
            "76": "$33240.07/pu",
            "77": "$23479.38/pu",
            "78": "$21688.86/pu",
            "79": "$18165.56/pu",
            "80": "$8000.00/pu",
            "81": "$8575.62/pu",
            "82": "$15762.42/pu",
            "83": "$14213.57/pu",
            "84": "$11814.25/pu",
            "85": "$10649.13/pu",
            "86": "$10649.13/pu",
            "87": "$10649.13/pu",
            "88": "$8495.08/pu",
            "89": "$6991.47/pu",
            "90": "$9000.00/pu",
            "91": "$11577.34/pu",
            "92": "$15498.85/pu",
            "93": "$14492.40/pu",
            "94": "$13623.63/pu",
            "95": "$13439.49/pu",
            "96": "$13207.42/pu",
            "97": "$10673.85/pu",
            "98": "$9795.27/pu",
            "99": "$11420.74/pu",
            "100": "$12770.76/pu",
            "101": "$13941.40/pu",
            "102": "$14980.32/pu",
            "103": "$40000.00/pu",
            "104": "$29856.71/pu",
            "105": "$30602.08/pu",
            "106": "$27534.14/pu",
            "107": "$29068.11/pu",
            "108": "$32454.78/pu",
            "109": "$33213.78/pu",
            "110": "$35221.98/pu",
            "111": "$35221.98/pu",
            "112": "$35221.98/pu",
            "113": "$34416.41/pu",
            "114": "$36323.72/pu",
            "115": "$36285.56/pu",
            "116": "$8889.88/pu",
            "117": "$34501.30/pu",
            "118": "$36827.78/pu"
        },
        "congestionamento_de_fluxo": {
            "1": {
                "limite_superior": -0.0,
                "limite_inferior": 0.0
            },
            "2": {
                "limite_superior": -0.0,
                "limite_inferior": 0.0
            },
            "3": {
                "limite_superior": -0.0,
                "limite_inferior": 0.0
            },
            "4": {
                "limite_superior": -0.0,
                "limite_inferior": 0.0
            },
            "5": {
                "limite_superior": -0.0,
                "limite_inferior": 0.0
            },
            "6": {
                "limite_superior": -0.0,
                "limite_inferior": 0.0
            },
            "7": {
                "limite_superior": -0.0,
                "limite_inferior": 0.0
            },
            "8": {
                "limite_superior": 45945.191,
                "limite_inferior": 0.0
            },
            "9": {
                "limite_superior": -0.0,
                "limite_inferior": 0.0
            },
            "10": {
                "limite_superior": -0.0,
                "limite_inferior": 0.0
            },
            "11": {
                "limite_superior": -0.0,
                "limite_inferior": 0.0
            },
            "12": {
                "limite_superior": -0.0,
                "limite_inferior": 0.0
            },
            "13": {
                "limite_superior": -0.0,
                "limite_inferior": 0.0
            },
            "14": {
                "limite_superior": -0.0,
                "limite_inferior": 0.0
            },
            "15": {
                "limite_superior": -0.0,
                "limite_inferior": 0.0
            },
            "16": {
                "limite_superior": -0.0,
                "limite_inferior": 0.0
            },
            "17": {
                "limite_superior": -0.0,
                "limite_inferior": 0.0
            },
            "18": {
                "limite_superior": -0.0,
                "limite_inferior": 0.0
            },
            "19": {
                "limite_superior": -0.0,
                "limite_inferior": 0.0
            },
            "20": {
                "limite_superior": -0.0,
                "limite_inferior": 0.0
            },
            "21": {
                "limite_superior": 39487.089,
                "limite_inferior": 0.0
            },
            "22": {
                "limite_superior": -0.0,
                "limite_inferior": 0.0
            },
            "23": {
                "limite_superior": -0.0,
                "limite_inferior": 0.0
            },
            "24": {
                "limite_superior": -0.0,
                "limite_inferior": 0.0
            },
            "25": {
                "limite_superior": -0.0,
                "limite_inferior": 0.0
            },
            "26": {
                "limite_superior": 44019.394,
                "limite_inferior": 0.0
            },
            "27": {
                "limite_superior": -0.0,
                "limite_inferior": 0.0
            },
            "28": {
                "limite_superior": -0.0,
                "limite_inferior": 0.0
            },
            "29": {
                "limite_superior": -0.0,
                "limite_inferior": 0.0
            },
            "30": {
                "limite_superior": -0.0,
                "limite_inferior": 42451.253
            },
            "31": {
                "limite_superior": -0.0,
                "limite_inferior": 0.0
            },
            "32": {
                "limite_superior": -0.0,
                "limite_inferior": 0.0
            },
            "33": {
                "limite_superior": -0.0,
                "limite_inferior": 0.0
            },
            "34": {
                "limite_superior": -0.0,
                "limite_inferior": 0.0
            },
            "35": {
                "limite_superior": -0.0,
                "limite_inferior": 0.0
            },
            "36": {
                "limite_superior": -0.0,
                "limite_inferior": 0.0
            },
            "37": {
                "limite_superior": 12331.823,
                "limite_inferior": 0.0
            },
            "38": {
                "limite_superior": -0.0,
                "limite_inferior": 0.0
            },
            "39": {
                "limite_superior": -0.0,
                "limite_inferior": 0.0
            },
            "40": {
                "limite_superior": -0.0,
                "limite_inferior": 0.0
            },
            "41": {
                "limite_superior": -0.0,
                "limite_inferior": 0.0
            },
            "42": {
                "limite_superior": -0.0,
                "limite_inferior": 0.0
            },
            "43": {
                "limite_superior": -0.0,
                "limite_inferior": 0.0
            },
            "44": {
                "limite_superior": -0.0,
                "limite_inferior": 0.0
            },
            "45": {
                "limite_superior": -0.0,
                "limite_inferior": 0.0
            },
            "46": {
                "limite_superior": -0.0,
                "limite_inferior": 0.0
            },
            "47": {
                "limite_superior": -0.0,
                "limite_inferior": 0.0
            },
            "48": {
                "limite_superior": -0.0,
                "limite_inferior": 0.0
            },
            "50": {
                "limite_superior": -0.0,
                "limite_inferior": 0.0
            },
            "51": {
                "limite_superior": -0.0,
                "limite_inferior": 0.0
            },
            "52": {
                "limite_superior": -0.0,
                "limite_inferior": 0.0
            },
            "53": {
                "limite_superior": -0.0,
                "limite_inferior": 0.0
            },
            "54": {
                "limite_superior": -0.0,
                "limite_inferior": 0.0
            },
            "55": {
                "limite_superior": -0.0,
                "limite_inferior": 0.0
            },
            "56": {
                "limite_superior": -0.0,
                "limite_inferior": 0.0
            },
            "57": {
                "limite_superior": -0.0,
                "limite_inferior": 0.0
            },
            "58": {
                "limite_superior": -0.0,
                "limite_inferior": 0.0
            },
            "59": {
                "limite_superior": -0.0,
                "limite_inferior": 0.0
            },
            "60": {
                "limite_superior": -0.0,
                "limite_inferior": 0.0
            },
            "61": {
                "limite_superior": -0.0,
                "limite_inferior": 0.0
            },
            "62": {
                "limite_superior": -0.0,
                "limite_inferior": 0.0
            },
            "63": {
                "limite_superior": -0.0,
                "limite_inferior": 0.0
            },
            "64": {
                "limite_superior": -0.0,
                "limite_inferior": 0.0
            },
            "65": {
                "limite_superior": -0.0,
                "limite_inferior": 0.0
            },
            "66": {
                "limite_superior": -0.0,
                "limite_inferior": 0.0
            },
            "67": {
                "limite_superior": -0.0,
                "limite_inferior": 0.0
            },
            "68": {
                "limite_superior": -0.0,
                "limite_inferior": 0.0
            },
            "69": {
                "limite_superior": -0.0,
                "limite_inferior": 0.0
            },
            "70": {
                "limite_superior": -0.0,
                "limite_inferior": 0.0
            },
            "71": {
                "limite_superior": -0.0,
                "limite_inferior": 0.0
            },
            "72": {
                "limite_superior": -0.0,
                "limite_inferior": 0.0
            },
            "73": {
                "limite_superior": -0.0,
                "limite_inferior": 0.0
            },
            "74": {
                "limite_superior": -0.0,
                "limite_inferior": 0.0
            },
            "75": {
                "limite_superior": -0.0,
                "limite_inferior": 0.0
            },
            "76": {
                "limite_superior": -0.0,
                "limite_inferior": 0.0
            },
            "77": {
                "limite_superior": -0.0,
                "limite_inferior": 0.0
            },
            "78": {
                "limite_superior": 41472.913,
                "limite_inferior": 0.0
            },
            "79": {
                "limite_superior": -0.0,
                "limite_inferior": 7521.0974
            },
            "80": {
                "limite_superior": -0.0,
                "limite_inferior": 0.0
            },
            "81": {
                "limite_superior": -0.0,
                "limite_inferior": 0.0
            },
            "82": {
                "limite_superior": -0.0,
                "limite_inferior": 0.0
            },
            "83": {
                "limite_superior": -0.0,
                "limite_inferior": 0.0
            },
            "84": {
                "limite_superior": -0.0,
                "limite_inferior": 0.0
            },
            "85": {
                "limite_superior": -0.0,
                "limite_inferior": 0.0
            },
            "86": {
                "limite_superior": -0.0,
                "limite_inferior": 0.0
            },
            "87": {
                "limite_superior": -0.0,
                "limite_inferior": 0.0
            },
            "88": {
                "limite_superior": -0.0,
                "limite_inferior": 0.0
            },
            "89": {
                "limite_superior": -0.0,
                "limite_inferior": 0.0
            },
            "90": {
                "limite_superior": -0.0,
                "limite_inferior": 0.0
            },
            "91": {
                "limite_superior": -0.0,
                "limite_inferior": 0.0
            },
            "92": {
                "limite_superior": -0.0,
                "limite_inferior": 0.0
            },
            "93": {
                "limite_superior": -0.0,
                "limite_inferior": 0.0
            },
            "94": {
                "limite_superior": -0.0,
                "limite_inferior": 0.0
            },
            "95": {
                "limite_superior": -0.0,
                "limite_inferior": 0.0
            },
            "96": {
                "limite_superior": -0.0,
                "limite_inferior": 0.0
            },
            "97": {
                "limite_superior": -0.0,
                "limite_inferior": 36953.266
            },
            "98": {
                "limite_superior": -0.0,
                "limite_inferior": 0.0
            },
            "99": {
                "limite_superior": 35488.17,
                "limite_inferior": 0.0
            },
            "100": {
                "limite_superior": -0.0,
                "limite_inferior": 0.0
            },
            "101": {
                "limite_superior": -0.0,
                "limite_inferior": 0.0
            },
            "102": {
                "limite_superior": -0.0,
                "limite_inferior": 0.0
            },
            "103": {
                "limite_superior": -0.0,
                "limite_inferior": 0.0
            },
            "104": {
                "limite_superior": -0.0,
                "limite_inferior": 4222.4364
            },
            "105": {
                "limite_superior": -0.0,
                "limite_inferior": 0.0
            },
            "106": {
                "limite_superior": -0.0,
                "limite_inferior": 0.0
            },
            "107": {
                "limite_superior": -0.0,
                "limite_inferior": 0.0
            },
            "108": {
                "limite_superior": -0.0,
                "limite_inferior": 0.0
            },
            "109": {
                "limite_superior": -0.0,
                "limite_inferior": 0.0
            },
            "110": {
                "limite_superior": -0.0,
                "limite_inferior": 0.0
            },
            "111": {
                "limite_superior": -0.0,
                "limite_inferior": 0.0
            },
            "112": {
                "limite_superior": -0.0,
                "limite_inferior": 0.0
            },
            "113": {
                "limite_superior": -0.0,
                "limite_inferior": 0.0
            },
            "114": {
                "limite_superior": -0.0,
                "limite_inferior": 0.0
            },
            "115": {
                "limite_superior": -0.0,
                "limite_inferior": 0.0
            },
            "116": {
                "limite_superior": 78424.065,
                "limite_inferior": 0.0
            },
            "117": {
                "limite_superior": -0.0,
                "limite_inferior": 0.0
            },
            "118": {
                "limite_superior": -0.0,
                "limite_inferior": 0.0
            },
            "119": {
                "limite_superior": -0.0,
                "limite_inferior": 0.0
            },
            "120": {
                "limite_superior": -0.0,
                "limite_inferior": 0.0
            },
            "121": {
                "limite_superior": -0.0,
                "limite_inferior": 0.0
            },
            "122": {
                "limite_superior": -0.0,
                "limite_inferior": 0.0
            },
            "123": {
                "limite_superior": -0.0,
                "limite_inferior": 34774.9
            },
            "124": {
                "limite_superior": -0.0,
                "limite_inferior": 0.0
            },
            "125": {
                "limite_superior": -0.0,
                "limite_inferior": 0.0
            },
            "126": {
                "limite_superior": -0.0,
                "limite_inferior": 0.0
            },
            "127": {
                "limite_superior": -0.0,
                "limite_inferior": 0.0
            },
            "128": {
                "limite_superior": -0.0,
                "limite_inferior": 0.0
            },
            "129": {
                "limite_superior": -0.0,
                "limite_inferior": 0.0
            },
            "130": {
                "limite_superior": -0.0,
                "limite_inferior": 0.0
            },
            "131": {
                "limite_superior": -0.0,
                "limite_inferior": 0.0
            },
            "132": {
                "limite_superior": -0.0,
                "limite_inferior": 0.0
            },
            "133": {
                "limite_superior": -0.0,
                "limite_inferior": 0.0
            },
            "134": {
                "limite_superior": -0.0,
                "limite_inferior": 0.0
            },
            "135": {
                "limite_superior": -0.0,
                "limite_inferior": 0.0
            },
            "136": {
                "limite_superior": -0.0,
                "limite_inferior": 0.0
            },
            "137": {
                "limite_superior": -0.0,
                "limite_inferior": 0.0
            },
            "138": {
                "limite_superior": -0.0,
                "limite_inferior": 0.0
            },
            "139": {
                "limite_superior": -0.0,
                "limite_inferior": 0.0
            },
            "140": {
                "limite_superior": -0.0,
                "limite_inferior": 0.0
            },
            "141": {
                "limite_superior": 14915.84,
                "limite_inferior": 0.0
            },
            "142": {
                "limite_superior": -0.0,
                "limite_inferior": 0.0
            },
            "143": {
                "limite_superior": -0.0,
                "limite_inferior": 0.0
            },
            "144": {
                "limite_superior": -0.0,
                "limite_inferior": 0.0
            },
            "145": {
                "limite_superior": -0.0,
                "limite_inferior": 0.0
            },
            "146": {
                "limite_superior": -0.0,
                "limite_inferior": 0.0
            },
            "147": {
                "limite_superior": -0.0,
                "limite_inferior": 0.0
            },
            "148": {
                "limite_superior": -0.0,
                "limite_inferior": 0.0
            },
            "149": {
                "limite_superior": -0.0,
                "limite_inferior": 0.0
            },
            "150": {
                "limite_superior": -0.0,
                "limite_inferior": 0.0
            },
            "151": {
                "limite_superior": -0.0,
                "limite_inferior": 0.0
            },
            "152": {
                "limite_superior": -0.0,
                "limite_inferior": 0.0
            },
            "153": {
                "limite_superior": -0.0,
                "limite_inferior": 0.0
            },
            "154": {
                "limite_superior": -0.0,
                "limite_inferior": 0.0
            },
            "155": {
                "limite_superior": -0.0,
                "limite_inferior": 0.0
            },
            "156": {
                "limite_superior": -0.0,
                "limite_inferior": 0.0
            },
            "157": {
                "limite_superior": -0.0,
                "limite_inferior": 0.0
            },
            "158": {
                "limite_superior": -0.0,
                "limite_inferior": 0.0
            },
            "159": {
                "limite_superior": -0.0,
                "limite_inferior": 0.0
            },
            "160": {
                "limite_superior": -0.0,
                "limite_inferior": 0.0
            },
            "161": {
                "limite_superior": -0.0,
                "limite_inferior": 0.0
            },
            "162": {
                "limite_superior": -0.0,
                "limite_inferior": 0.0
            },
            "163": {
                "limite_superior": 35010.974,
                "limite_inferior": 0.0
            },
            "164": {
                "limite_superior": -0.0,
                "limite_inferior": 0.0
            },
            "165": {
                "limite_superior": -0.0,
                "limite_inferior": 0.0
            },
            "166": {
                "limite_superior": -0.0,
                "limite_inferior": 0.0
            },
            "167": {
                "limite_superior": -0.0,
                "limite_inferior": 0.0
            },
            "168": {
                "limite_superior": -0.0,
                "limite_inferior": 0.0
            },
            "169": {
                "limite_superior": -0.0,
                "limite_inferior": 0.0
            },
            "170": {
                "limite_superior": -0.0,
                "limite_inferior": 0.0
            },
            "171": {
                "limite_superior": -0.0,
                "limite_inferior": 0.0
            },
            "172": {
                "limite_superior": -0.0,
                "limite_inferior": 0.0
            },
            "173": {
                "limite_superior": -0.0,
                "limite_inferior": 0.0
            },
            "174": {
                "limite_superior": -0.0,
                "limite_inferior": 0.0
            },
            "175": {
                "limite_superior": -0.0,
                "limite_inferior": 0.0
            },
            "176": {
                "limite_superior": -0.0,
                "limite_inferior": 0.0
            },
            "177": {
                "limite_superior": -0.0,
                "limite_inferior": 0.0
            },
            "178": {
                "limite_superior": -0.0,
                "limite_inferior": 0.0
            },
            "179": {
                "limite_superior": -0.0,
                "limite_inferior": 0.0
            },
            "180": {
                "limite_superior": -0.0,
                "limite_inferior": 0.0
            },
            "181": {
                "limite_superior": -0.0,
                "limite_inferior": 0.0
            },
            "182": {
                "limite_superior": -0.0,
                "limite_inferior": 0.0
            },
            "183": {
                "limite_superior": -0.0,
                "limite_inferior": 0.0
            },
            "184": {
                "limite_superior": -0.0,
                "limite_inferior": 0.0
            },
            "185": {
                "limite_superior": -0.0,
                "limite_inferior": 0.0
            },
            "186": {
                "limite_superior": -0.0,
                "limite_inferior": 0.0
            }
        },
        "limites_de_geracao": {
            "1": {
                "limite_superior": 36573.595,
                "limite_inferior": 0.0
            },
            "2": {
                "limite_superior": -0.0,
                "limite_inferior": 0.0
            },
            "3": {
                "limite_superior": 36946.804,
                "limite_inferior": 0.0
            },
            "4": {
                "limite_superior": -0.0,
                "limite_inferior": 0.0
            },
            "5": {
                "limite_superior": -0.0,
                "limite_inferior": 39200.0
            },
            "6": {
                "limite_superior": -0.0,
                "limite_inferior": 5498.703
            },
            "7": {
                "limite_superior": -0.0,
                "limite_inferior": 0.0
            },
            "8": {
                "limite_superior": -0.0,
                "limite_inferior": 2914.3779
            },
            "9": {
                "limite_superior": -0.0,
                "limite_inferior": 0.0
            },
            "10": {
                "limite_superior": -0.0,
                "limite_inferior": 0.0
            },
            "11": {
                "limite_superior": -0.0,
                "limite_inferior": 5493.2829
            },
            "12": {
                "limite_superior": -0.0,
                "limite_inferior": 8469.4825
            },
            "13": {
                "limite_superior": -0.0,
                "limite_inferior": 3986.3561
            },
            "14": {
                "limite_superior": -0.0,
                "limite_inferior": 4307.0294
            },
            "15": {
                "limite_superior": -0.0,
                "limite_inferior": 3451.697
            },
            "16": {
                "limite_superior": -0.0,
                "limite_inferior": 19999.827
            },
            "17": {
                "limite_superior": -0.0,
                "limite_inferior": 20627.198
            },
            "18": {
                "limite_superior": -0.0,
                "limite_inferior": 22565.749
            },
            "19": {
                "limite_superior": 11109.053,
                "limite_inferior": 0.0
            },
            "20": {
                "limite_superior": 7229.9846,
                "limite_inferior": 0.0
            },
            "21": {
                "limite_superior": 6665.1688,
                "limite_inferior": 0.0
            },
            "22": {
                "limite_superior": -0.0,
                "limite_inferior": 0.0
            },
            "23": {
                "limite_superior": -0.0,
                "limite_inferior": 0.0
            },
            "24": {
                "limite_superior": -0.0,
                "limite_inferior": 0.0
            },
            "25": {
                "limite_superior": -0.0,
                "limite_inferior": 1876.1916
            },
            "26": {
                "limite_superior": -0.0,
                "limite_inferior": 0.0
            },
            "27": {
                "limite_superior": -0.0,
                "limite_inferior": 3051.7278
            },
            "28": {
                "limite_superior": -0.0,
                "limite_inferior": 25778.278
            },
            "29": {
                "limite_superior": -0.0,
                "limite_inferior": 16519.002
            },
            "30": {
                "limite_superior": -0.0,
                "limite_inferior": 0.0
            },
            "31": {
                "limite_superior": -0.0,
                "limite_inferior": 17312.495
            },
            "32": {
                "limite_superior": -0.0,
                "limite_inferior": 27936.936
            },
            "33": {
                "limite_superior": -0.0,
                "limite_inferior": 19062.693
            },
            "34": {
                "limite_superior": -0.0,
                "limite_inferior": 4065.2823
            },
            "35": {
                "limite_superior": -0.0,
                "limite_inferior": 6759.933
            },
            "36": {
                "limite_superior": -0.0,
                "limite_inferior": 16520.617
            },
            "37": {
                "limite_superior": -0.0,
                "limite_inferior": 0.0
            },
            "38": {
                "limite_superior": 2149.1304,
                "limite_inferior": 0.0
            },
            "39": {
                "limite_superior": -0.0,
                "limite_inferior": 29350.87
            },
            "40": {
                "limite_superior": -0.0,
                "limite_inferior": 33008.532
            },
            "41": {
                "limite_superior": -0.0,
                "limite_inferior": 0.0
            },
            "42": {
                "limite_superior": -0.0,
                "limite_inferior": 28422.659
            },
            "43": {
                "limite_superior": -0.0,
                "limite_inferior": 24501.154
            },
            "44": {
                "limite_superior": -0.0,
                "limite_inferior": 28579.265
            },
            "45": {
                "limite_superior": -0.0,
                "limite_inferior": 27229.238
            },
            "46": {
                "limite_superior": -0.0,
                "limite_inferior": 0.0
            },
            "47": {
                "limite_superior": -0.0,
                "limite_inferior": 10143.291
            },
            "48": {
                "limite_superior": -0.0,
                "limite_inferior": 9397.9234
            },
            "49": {
                "limite_superior": -0.0,
                "limite_inferior": 10931.891
            },
            "50": {
                "limite_superior": -0.0,
                "limite_inferior": 4778.0244
            },
            "51": {
                "limite_superior": -0.0,
                "limite_inferior": 4778.0244
            },
            "52": {
                "limite_superior": -0.0,
                "limite_inferior": 4778.0244
            },
            "53": {
                "limite_superior": -0.0,
                "limite_inferior": 5583.5863
            },
            "54": {
                "limite_superior": -0.0,
                "limite_inferior": 31110.12
            },
            "55": {
                "limite_superior": 36673.595,
                "limite_inferior": 0.0
            },
            "56": {
                "limite_superior": 800.0,
                "limite_inferior": 0.0
            },
            "57": {
                "limite_superior": 1500.0,
                "limite_inferior": 0.0
            },
            "58": {
                "limite_superior": 2400.0,
                "limite_inferior": 0.0
            },
            "59": {
                "limite_superior": 5400.0,
                "limite_inferior": 0.0
            },
            "60": {
                "limite_superior": 38123.808,
                "limite_inferior": 0.0
            },
            "61": {
                "limite_superior": 6900.0,
                "limite_inferior": 0.0
            },
            "62": {
                "limite_superior": 35934.718,
                "limite_inferior": 0.0
            },
            "63": {
                "limite_superior": 8000.0,
                "limite_inferior": 0.0
            },
            "64": {
                "limite_superior": 10649.13,
                "limite_inferior": 0.0
            },
            "65": {
                "limite_superior": 35221.976,
                "limite_inferior": 0.0
            },
            "1001": {
                "limite_superior": -0.0,
                "limite_inferior": 3326.4051
            },
            "1002": {
                "limite_superior": -0.0,
                "limite_inferior": 4670.1361
            },
            "1003": {
                "limite_superior": -0.0,
                "limite_inferior": 2756.0928
            },
            "1004": {
                "limite_superior": -0.0,
                "limite_inferior": 0.0
            },
            "1005": {
                "limite_superior": -0.0,
                "limite_inferior": 2453.1959
            },
            "1006": {
                "limite_superior": -0.0,
                "limite_inferior": 3609.1548
            },
            "1007": {
                "limite_superior": -0.0,
                "limite_inferior": 4723.3295
            },
            "1008": {
                "limite_superior": -0.0,
                "limite_inferior": 5498.703
            },
            "1009": {
                "limite_superior": -0.0,
                "limite_inferior": 12499.942
            },
            "1010": {
                "limite_superior": -0.0,
                "limite_inferior": 14280.004
            },
            "1011": {
                "limite_superior": -0.0,
                "limite_inferior": 38500.0
            },
            "1012": {
                "limite_superior": -0.0,
                "limite_inferior": 5625.6201
            },
            "1013": {
                "limite_superior": -0.0,
                "limite_inferior": 5899.6941
            },
            "1014": {
                "limite_superior": -0.0,
                "limite_inferior": 2914.3779
            },
            "1015": {
                "limite_superior": -0.0,
                "limite_inferior": 0.0
            },
            "1016": {
                "limite_superior": -0.0,
                "limite_inferior": 1.8599913e-09
            },
            "1017": {
                "limite_superior": -0.0,
                "limite_inferior": -1.8956421e-10
            },
            "1018": {
                "limite_superior": -0.0,
                "limite_inferior": -2.5399631e-09
            },
            "1019": {
                "limite_superior": -0.0,
                "limite_inferior": 0.0
            },
            "1020": {
                "limite_superior": -0.0,
                "limite_inferior": 3986.3561
            },
            "1021": {
                "limite_superior": -0.0,
                "limite_inferior": 4115.1375
            },
            "1022": {
                "limite_superior": -0.0,
                "limite_inferior": 4257.1736
            },
            "1023": {
                "limite_superior": -0.0,
                "limite_inferior": 4307.0294
            },
            "1024": {
                "limite_superior": -0.0,
                "limite_inferior": 3451.697
            },
            "1025": {
                "limite_superior": -0.0,
                "limite_inferior": 30153.992
            },
            "1026": {
                "limite_superior": -0.0,
                "limite_inferior": 19999.827
            },
            "1027": {
                "limite_superior": -0.0,
                "limite_inferior": 20627.198
            },
            "1028": {
                "limite_superior": -0.0,
                "limite_inferior": 20627.198
            },
            "1029": {
                "limite_superior": -0.0,
                "limite_inferior": 21861.351
            },
            "1030": {
                "limite_superior": -0.0,
                "limite_inferior": 22565.749
            },
            "1031": {
                "limite_superior": -0.0,
                "limite_inferior": 23129.152
            },
            "1032": {
                "limite_superior": -0.0,
                "limite_inferior": 24690.947
            },
            "1033": {
                "limite_superior": -0.0,
                "limite_inferior": 22391.782
            },
            "1034": {
                "limite_superior": -0.0,
                "limite_inferior": 25883.665
            },
            "1035": {
                "limite_superior": -0.0,
                "limite_inferior": 27165.73
            },
            "1036": {
                "limite_superior": -0.0,
                "limite_inferior": 28170.015
            },
            "1037": {
                "limite_superior": -0.0,
                "limite_inferior": 28970.183
            },
            "1038": {
                "limite_superior": -0.0,
                "limite_inferior": 28378.993
            },
            "1039": {
                "limite_superior": -0.0,
                "limite_inferior": 28434.831
            },
            "1040": {
                "limite_superior": -0.0,
                "limite_inferior": 21442.355
            },
            "1041": {
                "limite_superior": -0.0,
                "limite_inferior": 19087.807
            },
            "1042": {
                "limite_superior": -0.0,
                "limite_inferior": 21736.999
            },
            "1043": {
                "limite_superior": -0.0,
                "limite_inferior": 29103.376
            },
            "1044": {
                "limite_superior": -0.0,
                "limite_inferior": 34600.0
            },
            "1045": {
                "limite_superior": -0.0,
                "limite_inferior": 0.0
            },
            "1046": {
                "limite_superior": -0.0,
                "limite_inferior": 0.0
            },
            "1047": {
                "limite_superior": -0.0,
                "limite_inferior": 8982.3567
            },
            "1048": {
                "limite_superior": -0.0,
                "limite_inferior": 10942.921
            },
            "1049": {
                "limite_superior": -0.0,
                "limite_inferior": 1876.1916
            },
            "1050": {
                "limite_superior": -0.0,
                "limite_inferior": 681.57915
            },
            "1051": {
                "limite_superior": -0.0,
                "limite_inferior": 3051.7278
            },
            "1052": {
                "limite_superior": -0.0,
                "limite_inferior": 16519.002
            },
            "1053": {
                "limite_superior": -0.0,
                "limite_inferior": 10263.037
            },
            "1054": {
                "limite_superior": -0.0,
                "limite_inferior": 17312.495
            },
            "1055": {
                "limite_superior": -0.0,
                "limite_inferior": 4065.2823
            },
            "1056": {
                "limite_superior": -0.0,
                "limite_inferior": 0.0
            },
            "1057": {
                "limite_superior": -0.0,
                "limite_inferior": 6759.933
            },
            "1058": {
                "limite_superior": -0.0,
                "limite_inferior": 16520.617
            },
            "1059": {
                "limite_superior": -0.0,
                "limite_inferior": 18311.142
            },
            "1060": {
                "limite_superior": -0.0,
                "limite_inferior": 21834.435
            },
            "1061": {
                "limite_superior": -0.0,
                "limite_inferior": 32000.0
            },
            "1062": {
                "limite_superior": -0.0,
                "limite_inferior": 24237.575
            },
            "1063": {
                "limite_superior": -0.0,
                "limite_inferior": 25786.429
            },
            "1064": {
                "limite_superior": -0.0,
                "limite_inferior": 28185.747
            },
            "1065": {
                "limite_superior": -0.0,
                "limite_inferior": 29350.87
            },
            "1066": {
                "limite_superior": -0.0,
                "limite_inferior": 29350.87
            },
            "1067": {
                "limite_superior": -0.0,
                "limite_inferior": 31504.92
            },
            "1068": {
                "limite_superior": -0.0,
                "limite_inferior": 31000.0
            },
            "1069": {
                "limite_superior": -0.0,
                "limite_inferior": 24501.154
            },
            "1070": {
                "limite_superior": -0.0,
                "limite_inferior": 25507.6
            },
            "1071": {
                "limite_superior": -0.0,
                "limite_inferior": 26376.371
            },
            "1072": {
                "limite_superior": -0.0,
                "limite_inferior": 26560.507
            },
            "1073": {
                "limite_superior": -0.0,
                "limite_inferior": 26792.585
            },
            "1074": {
                "limite_superior": -0.0,
                "limite_inferior": 29326.154
            },
            "1075": {
                "limite_superior": -0.0,
                "limite_inferior": 30204.731
            },
            "1076": {
                "limite_superior": -0.0,
                "limite_inferior": 27229.238
            },
            "1077": {
                "limite_superior": -0.0,
                "limite_inferior": 26058.601
            },
            "1078": {
                "limite_superior": -0.0,
                "limite_inferior": 25019.685
            },
            "1079": {
                "limite_superior": -0.0,
                "limite_inferior": -1.1793373e-12
            },
            "1080": {
                "limite_superior": -0.0,
                "limite_inferior": 10143.291
            },
            "1081": {
                "limite_superior": -0.0,
                "limite_inferior": 9397.9234
            },
            "1082": {
                "limite_superior": -0.0,
                "limite_inferior": 12465.859
            },
            "1083": {
                "limite_superior": -0.0,
                "limite_inferior": 10931.891
            },
            "1084": {
                "limite_superior": -0.0,
                "limite_inferior": 7545.22
            },
            "1085": {
                "limite_superior": -0.0,
                "limite_inferior": 6786.2178
            },
            "1086": {
                "limite_superior": -0.0,
                "limite_inferior": 4778.0244
            },
            "1087": {
                "limite_superior": -0.0,
                "limite_inferior": 4778.0244
            },
            "1088": {
                "limite_superior": -0.0,
                "limite_inferior": 3676.2758
            },
            "1089": {
                "limite_superior": -0.0,
                "limite_inferior": 3714.4395
            },
            "1090": {
                "limite_superior": -0.0,
                "limite_inferior": 5498.703
            },
            "1091": {
                "limite_superior": -0.0,
                "limite_inferior": 3172.2222
            }
        }
    }
}